subwabbit/CHANGELOG.md
subwabbit/__init__.py
subwabbit/base.py
subwabbit/blocking.py
subwabbit/nonblocking.py
subwabbit/version.py
subwabbit-2.0.0.dist-info/LICENSE
subwabbit-2.0.0.dist-info/METADATA
subwabbit-2.0.0.dist-info/WHEEL
subwabbit-2.0.0.dist-info/top_level.txt
subwabbit-2.0.0.dist-info/RECORD
