Metadata-Version: 2.1
Name: subwabbit
Version: 2.0.0
Summary: Fast Python Vowpal Wabbit wrapper
Home-page: https://github.com/jakac/subwabbit
Author: Matej Jakimov
Author-email: matej.jakimov@gmail.com
License: BSD
Platform: UNKNOWN
Classifier: Programming Language :: Python :: 3.4
Classifier: Programming Language :: Python :: 3.5
Classifier: Programming Language :: Python :: 3.6
Classifier: Programming Language :: Python :: 3.7
Classifier: License :: OSI Approved :: BSD License
Classifier: Development Status :: 5 - Production/Stable
Classifier: Intended Audience :: Developers
Classifier: Topic :: Software Development :: Libraries
Requires-Dist: mypy-lang
Requires-Dist: typing
